Workbook

Sheet 1601-C
A1: Republic of the Philippines Department of Finance Bureau of Internal Revenue | D1: BIR Form No.
D2: 1601-C
A3: Monthly Remittance Return of Income Taxes Withheld on Compensation
A4: January 2018 (ENCS)
A5: Fill in all applicable fields. All figures should be in Philippine Peso.
A7: Part I — Background Information
A8: 1 | B8: TIN
A9: 2 | B9: RDO Code
A10: 3 | B10: Withholding Agent's Name
A11: 4 | B11: Registered Address
A12: 5 | B12: Zip Code
A13: 6 | B13: Category of Withholding Agent
A14: 7 | B14: For the Month (MM/YYYY)
A15: 9 | B15: Amendment? (Yes/No) | E15: If Yes, Date
A16: 10 | B16: ATC | D16: WI010
A18: Part II — Computation of Tax
A19: A. Tax Remitted in Return Previously Filed, if this is an Amended Return
A20: 11 | B20: Total Amount of Compensation
A21: 12 | B21: Exemptions/De Minimis/SSS/GSIS/PhilHealth/Pag-IBIG
A22: 13 | B22: Taxable Compensation (Item 11 less Item 12) | F22: =F20-F21
A24: B. Tax Required to be Withheld and Remitted this Period
A25: 14 | B25: Taxes Withheld for the Month
A26: 15 | B26: Adjustment, if any (From previous month/s — Overremittance) | F26: 0
A27: 16 | B27: Adjustment, if any (From previous month/s — Underremittance) | F27: 0
A28: 17 | B28: Tax Still Due / (Overremittance) (Item 14 - 15 + 16) | F28: =F25-F26+F27
A30: C. Penalties
A31: 18 | B31: Surcharge | F31: 0
A32: 19 | B32: Interest | F32: 0
A33: 20 | B33: Compromise | F33: 0
A35: 21 | B35: TOTAL AMOUNT STILL DUE / (Overremittance) | F35: =F28+F31+F32+F33
A37: Part III — Details of Payment
A38: 22 | B38: Drawee Bank / Agency
A39: 23 | B39: Number
A40: 24 | B40: Date (MM/DD/YYYY)
A41: 25 | B41: Amount
A43: DECLARATION
A44: I declare, under the penalties of perjury, that this return has been made in good faith, verified by me, and to the best of my knowledge and belief, is true and correct, pursuant to the provisions of the National Internal Revenue Code, as amended, and the regulations issued under authority thereof.
B46: Signature over Printed Name of Withholding Agent/Authorized Representative
B47: Title/Position
B48: TIN of Signatory | E48: Date

Sheet eFPS Ready
A1: eFPS Filing Data — BIR 1601-C
A2: Copy values below into eFPS portal fields
A4: Form Type | B4: 1601-C
A5: TIN | B5: ='1601-C'!D8
A6: Return Period | B6: ='1601-C'!D14
A7: Total Compensation | B7: ='1601-C'!F20
A8: Exemptions/Deductions | B8: ='1601-C'!F21
A9: Taxable Compensation | B9: ='1601-C'!F22
A10: Taxes Withheld | B10: ='1601-C'!F25
A11: Over-remittance Adj | B11: ='1601-C'!F26
A12: Under-remittance Adj | B12: ='1601-C'!F27
A13: Tax Still Due | B13: ='1601-C'!F28
A14: Surcharge | B14: ='1601-C'!F31
A15: Interest | B15: ='1601-C'!F32
A16: Compromise | B16: ='1601-C'!F33
A17: TOTAL AMOUNT DUE | B17: ='1601-C'!F35

Sheet Schedule - Employees
A1: Employee Name | B1: TIN | C1: Monthly Basic | D1: SSS EE | E1: PhilHealth EE | F1: Pag-IBIG EE | G1: Taxable Comp | H1: WTax Due
G2: =MAX(C2-D2-E2-F2,0) | H2: =IF(G2<=20833,0,IF(G2<=33333,(G2-20833)*0.15,IF(G2<=66667,1875+(G2-33333)*0.2,IF(G2<=166667,8542+(G2-66667)*0.25,IF(G2<=666667,33542+(G2-166667)*0.3,183542+(G2-666667)*0.35)))))
G3: =MAX(C3-D3-E3-F3,0) | H3: =IF(G3<=20833,0,IF(G3<=33333,(G3-20833)*0.15,IF(G3<=66667,1875+(G3-33333)*0.2,IF(G3<=166667,8542+(G3-66667)*0.25,IF(G3<=666667,33542+(G3-166667)*0.3,183542+(G3-666667)*0.35)))))
G4: =MAX(C4-D4-E4-F4,0) | H4: =IF(G4<=20833,0,IF(G4<=33333,(G4-20833)*0.15,IF(G4<=66667,1875+(G4-33333)*0.2,IF(G4<=166667,8542+(G4-66667)*0.25,IF(G4<=666667,33542+(G4-166667)*0.3,183542+(G4-666667)*0.35)))))
G5: =MAX(C5-D5-E5-F5,0) | H5: =IF(G5<=20833,0,IF(G5<=33333,(G5-20833)*0.15,IF(G5<=66667,1875+(G5-33333)*0.2,IF(G5<=166667,8542+(G5-66667)*0.25,IF(G5<=666667,33542+(G5-166667)*0.3,183542+(G5-666667)*0.35)))))
G6: =MAX(C6-D6-E6-F6,0) | H6: =IF(G6<=20833,0,IF(G6<=33333,(G6-20833)*0.15,IF(G6<=66667,1875+(G6-33333)*0.2,IF(G6<=166667,8542+(G6-66667)*0.25,IF(G6<=666667,33542+(G6-166667)*0.3,183542+(G6-666667)*0.35)))))
G7: =MAX(C7-D7-E7-F7,0) | H7: =IF(G7<=20833,0,IF(G7<=33333,(G7-20833)*0.15,IF(G7<=66667,1875+(G7-33333)*0.2,IF(G7<=166667,8542+(G7-66667)*0.25,IF(G7<=666667,33542+(G7-166667)*0.3,183542+(G7-666667)*0.35)))))
G8: =MAX(C8-D8-E8-F8,0) | H8: =IF(G8<=20833,0,IF(G8<=33333,(G8-20833)*0.15,IF(G8<=66667,1875+(G8-33333)*0.2,IF(G8<=166667,8542+(G8-66667)*0.25,IF(G8<=666667,33542+(G8-166667)*0.3,183542+(G8-666667)*0.35)))))
G9: =MAX(C9-D9-E9-F9,0) | H9: =IF(G9<=20833,0,IF(G9<=33333,(G9-20833)*0.15,IF(G9<=66667,1875+(G9-33333)*0.2,IF(G9<=166667,8542+(G9-66667)*0.25,IF(G9<=666667,33542+(G9-166667)*0.3,183542+(G9-666667)*0.35)))))
G10: =MAX(C10-D10-E10-F10,0) | H10: =IF(G10<=20833,0,IF(G10<=33333,(G10-20833)*0.15,IF(G10<=66667,1875+(G10-33333)*0.2,IF(G10<=166667,8542+(G10-66667)*0.25,IF(G10<=666667,33542+(G10-166667)*0.3,183542+(G10-666667)*0.35)))))
G11: =MAX(C11-D11-E11-F11,0) | H11: =IF(G11<=20833,0,IF(G11<=33333,(G11-20833)*0.15,IF(G11<=66667,1875+(G11-33333)*0.2,IF(G11<=166667,8542+(G11-66667)*0.25,IF(G11<=666667,33542+(G11-166667)*0.3,183542+(G11-666667)*0.35)))))
G12: =MAX(C12-D12-E12-F12,0) | H12: =IF(G12<=20833,0,IF(G12<=33333,(G12-20833)*0.15,IF(G12<=66667,1875+(G12-33333)*0.2,IF(G12<=166667,8542+(G12-66667)*0.25,IF(G12<=666667,33542+(G12-166667)*0.3,183542+(G12-666667)*0.35)))))
G13: =MAX(C13-D13-E13-F13,0) | H13: =IF(G13<=20833,0,IF(G13<=33333,(G13-20833)*0.15,IF(G13<=66667,1875+(G13-33333)*0.2,IF(G13<=166667,8542+(G13-66667)*0.25,IF(G13<=666667,33542+(G13-166667)*0.3,183542+(G13-666667)*0.35)))))
... G21: =MAX(C21-D21-E21-F21,0) | H21: =IF(G21<=20833,0,IF(G21<=33333,(G21-20833)*0.15,IF(G21<=66667,1875+(G21-33333)*0.2,IF(G21<=166667,8542+(G21-66667)*0.25,IF(G21<=666667,33542+(G21-166667)*0.3,183542+(G21-666667)*0.35)))))
A22: TOTALS | C22: =SUM(C2:C21) | D22: =SUM(D2:D21) | E22: =SUM(E2:E21) | F22: =SUM(F2:F21) | G22: =SUM(G2:G21) | H22: =SUM(H2:H21)
